README.md
setup.py
src/loggingextras/ApiLogger.py
src/loggingextras/NoneLogger.py
src/loggingextras/__init__.py
src/loggingextras/levels.py
src/loggingextras.egg-info/PKG-INFO
src/loggingextras.egg-info/SOURCES.txt
src/loggingextras.egg-info/dependency_links.txt
src/loggingextras.egg-info/not-zip-safe
src/loggingextras.egg-info/top_level.txt
src/loggingextras/apilog/__init__.py
src/loggingextras/apilog/apilog.py
test/test_ApiLogger.py
test/test_NoneLogger.py
test/test_apilog_class_methods.py
test/test_apilog_methods.py