Metadata-Version: 1.0
Name: loggingextras
Version: 1.0
Summary: Extra Logging Functionality
Home-page: https://github.com/sharonlev/pyLoggingExtras
Author: Sharon Lev
Author-email: sharon_lev@yahoo.com
License:                     GNU GENERAL PUBLIC LICENSE
